testlodge/__init__.py
testlodge/_constants.py
testlodge/api/__init__.py
testlodge/api/base.py
testlodge/api/case.py
testlodge/api/custom_field.py
testlodge/api/plan.py
testlodge/api/plan_content.py
testlodge/api/project.py
testlodge/api/requirement.py
testlodge/api/requirement_document.py
testlodge/api/run.py
testlodge/api/suite.py
testlodge/api/suite_section.py
testlodge/api/user.py
testlodge/client/__init__.py
testlodge/client/base.py
testlodge/client/custom_field.py
testlodge/client/project.py
testlodge/client/user.py
testlodge/typing/__init__.py
testlodge/typing/case.py
testlodge/typing/custom_field.py
testlodge/typing/plan.py
testlodge/typing/plan_content.py
testlodge/typing/project.py
testlodge/typing/requirement.py
testlodge/typing/requirement_document.py
testlodge/typing/run.py
testlodge/typing/shared.py
testlodge/typing/suite.py
testlodge/typing/suite_section.py
testlodge/typing/user.py
testlodge-0.0.40.dist-info/LICENSE
testlodge-0.0.40.dist-info/METADATA
testlodge-0.0.40.dist-info/WHEEL
testlodge-0.0.40.dist-info/top_level.txt
testlodge-0.0.40.dist-info/RECORD
