Metadata-Version: 2.1
Name: testlodge
Version: 0.0.40
Summary: Python client library for interacting with TestLodge.
Home-page: https://github.com/AceofSpades5757/testlodge
Author: Kyle L. Davis
Author-email: AceofSpades5757.github@gmail.com
License: MIT
Project-URL: Documentation, https://testlodge.readthedocs.io/en/latest/
Project-URL: Author, https://github.com/AceofSpades5757
Platform: UNKNOWN
Classifier: License :: OSI Approved :: MIT License
Classifier: Development Status :: 2 - Pre-Alpha
Classifier: Operating System :: OS Independent
Classifier: Operating System :: Microsoft :: Windows
Classifier: Operating System :: POSIX :: Linux
Classifier: Programming Language :: Python :: 3
Classifier: Programming Language :: Python :: 3.8
Classifier: Programming Language :: Python :: 3.9
Classifier: Programming Language :: Python :: 3.10
Requires-Python: >=3.8
License-File: LICENSE
